{
    "nombre": "Luis A. Comas",
    "imgPerfil": "assets/img/perfil.jpg",
    "image": "",
    "titulo1": "Programador Visual FoxPro",
    "titulo2": "Programador Full Stack Jr",
    "titulo3": "Fotógrafo profesional",
    "company": {
        "name": "UNT",
        "img": "",
        "url": "http://"
    },
    "school": {
        "name": "Universidad Nacional de Tucumán",
        "img": "http://",
        "url": "#"
    },
    "ubicacion": "Tucumán (Argentina)",
    "about": "Programador, Fotógrafo",
    "experiencia": [{
        "position": "Programador",
        "company": "UNT",
        "img": "",
        "mode": "Jornada parcial",
        "start": "mar 1997",
        "end": "mar 2000",
        "timelapsed": "3 años"
    }],
    "educacion": [{
            "school": "UNT",
            "title": "Tecnico Constructo",
            "img": "http://",
            "carrera": "Tecnico",
            "score": 0,
            "starr": "1991",
            "end": "1997"
        },
        {
            "school": "UNT",
            "title": "Tecnico Constructor",
            "img": "http://",
            "carrera": "Tecnico",
            "score": 0,
            "starr": "1991",
            "end": "1997"
        }
    ],
    "skills": [{
            "name":"Photoshop",
            "progres": 75,
            "confirms": 2,
            "confirmsNames": [{
                "name":"Luis Comas"
            }]
        },
        {
            "name":"Lightroom",
            "progres": 65,
            "confirms": 3,
            "confirmsNames": [{
                "name":"Luis Comas"
            }]
        }
    ],
    "achivements": [{
            "name": "Luis Comas"
        },
        {
            "name": "xxxx 9/9"
        }
    ]
}

